h5xplorer/__init__.py
h5xplorer/__version__.py
h5xplorer/default_menu.py
h5xplorer/h5xplorer.py
h5xplorer/menu_plot.py
h5xplorer/menu_tools.py
h5xplorer/standarddialogs.py
h5xplorer-0.1.0.dist-info/METADATA
h5xplorer-0.1.0.dist-info/WHEEL
h5xplorer-0.1.0.dist-info/top_level.txt
h5xplorer-0.1.0.dist-info/RECORD
